url_local/__init__.py
url_local/action_name_enum.py
url_local/brand_name_enum.py
url_local/component_name_enum.py
url_local/entity_name_enum.py
url_local/environment_name_enum.py
url_local/url_circlez.py
url_local-0.0.50.dist-info/METADATA
url_local-0.0.50.dist-info/WHEEL
url_local-0.0.50.dist-info/top_level.txt
url_local-0.0.50.dist-info/RECORD
