Metadata-Version: 2.1
Name: url-local
Version: 0.0.50
Home-page: https://github.com/circles-zone/url-local-python-package
Author: Circles
Author-email: info@circles.life
Classifier: Programming Language :: Python :: 3
Classifier: License :: Other/Proprietary License
Classifier: Operating System :: OS Independent
Requires-Dist: python-dotenv >=1.0.0
Requires-Dist: pytest >=7.4.1
Requires-Dist: database-without-orm-local >=0.0.79
Requires-Dist: logger-local >=0.0.59
Requires-Dist: queue-local >=0.0.13
